mcp_server/__init__.py
mcp_server/__main__.py
mcp_server/agent.py
mcp_server/server.py
mcp_server/test/__init__.py
mcp_server/test/test_agent.py
mseep_ifly_spark_agent_mcp-0.1.4.dist-info/METADATA
mseep_ifly_spark_agent_mcp-0.1.4.dist-info/WHEEL
mseep_ifly_spark_agent_mcp-0.1.4.dist-info/entry_points.txt
mseep_ifly_spark_agent_mcp-0.1.4.dist-info/licenses/LICENSE
mseep_ifly_spark_agent_mcp-0.1.4.dist-info/RECORD
